adsb_tools/__init__.py
adsb_tools/aircraft.py
adsb_tools/receiver.py
adsb_tools/timezone.py
adsb_tools/wake_vortex.py
adsb_tools/weather.py
adsb_tools/static/README.md
adsb_tools/static/airports.csv
adsb_tools/static/wake_vortex_categories.csv
adsb_tools/static/utils/README.md
adsb_tools/static/utils/airport_convert.py
adsb_tools/static/utils/airport_extract.py
adsb_tools/utils/__init__.py
adsb_tools/utils/aeroapi_utils.py
adsb_tools/utils/dt_utils.py
adsb_tools/utils/requests_utils.py
adsb_tools/utils/spatial_utils.py
adsb_tools-0.1.55.dist-info/METADATA
adsb_tools-0.1.55.dist-info/WHEEL
adsb_tools-0.1.55.dist-info/RECORD
